CHANGES
MANIFEST.in
README
setup.py
routr/__init__.py
routr/exc.py
routr/static.py
routr/tests.py
routr/urlpattern.py
routr/utils.py
routr.egg-info/PKG-INFO
routr.egg-info/SOURCES.txt
routr.egg-info/dependency_links.txt
routr.egg-info/not-zip-safe
routr.egg-info/requires.txt
routr.egg-info/top_level.txt