Metadata-Version: 1.1
Name: routr
Version: 0.7.2
Summary: URL routing made right
Home-page: http://routr.readthedocs.org/
Author: Andrey Popp
Author-email: 8mayday@gmail.com
License: BSD
Keywords: routr routes routing webob
Platform: UNKNOWN
Classifier: Development Status :: 4 - Beta
Classifier: Environment :: Web Environment
Classifier: Operating System :: OS Independent
Classifier: Programming Language :: Python :: 2.6
Classifier: Programming Language :: Python :: 2.7
Classifier: Programming Language :: Python :: 3.2
Classifier: Programming Language :: Python :: 3.3
Classifier: Programming Language :: Python :: Implementation :: PyPy
Classifier: Topic :: Internet :: WWW/HTTP :: WSGI
